MANIFEST.in
README.md
VERSION
setup.py
hitchbuildvagrant/__init__.py
hitchbuildvagrant/box.py
hitchbuildvagrant/snapshot.py
hitchbuildvagrant/utils.py
hitchbuildvagrant.egg-info/PKG-INFO
hitchbuildvagrant.egg-info/SOURCES.txt
hitchbuildvagrant.egg-info/dependency_links.txt
hitchbuildvagrant.egg-info/not-zip-safe
hitchbuildvagrant.egg-info/requires.txt
hitchbuildvagrant.egg-info/top_level.txt
hitchbuildvagrant/templates/boxdata.json
hitchbuildvagrant/templates/linux.jinja2
hitchbuildvagrant/templates/macos-elcapitan.jinja2
hitchbuildvagrant/templates/macos-sierra.jinja2